{
  "generator": "fresh-vite-app-svelte-ts",
  "size": 69427636,
  "timing": {
    "startTime": "2024-05-06T01:07:26.942Z",
    "finishTime": "2024-05-06T01:07:38.224Z"
  },
  "log": [
    "node@factory:/workspace$ bash -exc 'pnpm create vite fresh-app --template=svelte-ts\r",
    "> cd fresh-app\r",
    "> corepack use pnpm@latest\r",
    "> pnpm build' < /dev/null; cat /opt/factory/src/completed.txt\r",
    "+ pnpm create vite fresh-app --template=svelte-ts\r",
    ".../18f4b70ffa1-b                        |   \u001b[32m+1\u001b[0m \u001b[32m+\r",
    "\u001b[0m.../18f4b70ffa1-b                        | Progress: resolved \u001b[96m1\u001b[0m, reused \u001b[96m0\u001b[0m, downloaded \u001b[96m1\u001b[0m, added \u001b[96m1\u001b[0m, done\r",
    "\r",
    "Scaffolding project in /workspace/fresh-app...\r",
    "\r",
    "Done. Now run:\r",
    "\r",
    "  cd fresh-app\r",
    "  pnpm install\r",
    "  pnpm run dev\r",
    "\r",
    "+ cd fresh-app\r",
    "+ corepack use pnpm@latest\r",
    "Installing pnpm@9.0.6 in the project...\r",
    "\r",
    "Downloading \u001b[97mtypescript@5.4.5\u001b[0m: \u001b[96m5.83 MB\u001b[0m/\u001b[96m5.83 MB\u001b[0m, done\r",
    "Packages: \u001b[32m+96\r",
    "++++++++++++++++++++++++++++++++++++++++++++++++++++++++++++++++++++++++++++++++++++++++++++++++\r",
    "\u001b[0mProgress: resolved \u001b[96m133\u001b[0m, reused \u001b[96m2\u001b[0m, downloaded \u001b[96m94\u001b[0m, added \u001b[96m96\u001b[0m, done\r",
    "\u001b[90mnode_modules/.pnpm/esbuild@0.20.2/node_modules/\u001b[0mesbuild: Running postinstall script...\r",
    "\u001b[90mnode_modules/.pnpm/svelte-preprocess@5.1.4_postcss@8.4.38_svelte@4.2.15_typescript@5.4.5/node_modules/\u001b[0msvelte-preprocess:\u001b[90mnode_modules/.pnpm/esbuild@0.20.2/node_modules/\u001b[0mesbuild: Running postinstall script, done in 52ms\u001b[90mdules/\u001b[0msvelte-preprocess:\r",
    " Running postinstall script, done in 11ms\r",
    "\r",
    "\u001b[96mdevDependencies:\r",
    "\u001b[32m+\u001b[0m @sveltejs/vite-plugin-svelte \u001b[90m3.1.0\r",
    "\u001b[32m+\u001b[0m @tsconfig/svelte \u001b[90m5.0.4\r",
    "\u001b[32m+\u001b[0m svelte \u001b[90m4.2.15\r",
    "\u001b[32m+\u001b[0m svelte-check \u001b[90m3.7.1\r",
    "\u001b[32m+\u001b[0m tslib \u001b[90m2.6.2\r",
    "\u001b[32m+\u001b[0m typescript \u001b[90m5.4.5\r",
    "\u001b[32m+\u001b[0m vite \u001b[90m5.2.11\r",
    "\r",
    "\u001b[0mDone in 2.3s\r",
    "+ pnpm build\r",
    "\r",
    "> fresh-app@0.0.0 build /workspace/fresh-app\r",
    "> vite build\r",
    "\r",
    "\u001b[36mvite v5.2.11 \u001b[32mbuilding for production...\r",
    "✓\u001b[0m 31 modules transformed.\r",
    "\u001b[2mdist/\u001b[32;22mindex.html                 \u001b[39;1;2m0.46 kB\u001b[22m │ gzip: 0.30 kB\r",
    "dist/assets/\u001b[35;22mindex-DDqFzPXY.css  \u001b[39;1;2m1.27 kB\u001b[22m │ gzip: 0.63 kB\r",
    "dist/assets/\u001b[36;22mindex-CWwFz4T6.js   \u001b[39;1;2m8.09 kB\u001b[22m │ gzip: 3.69 kB\r",
    "\u001b[32;22m✓ built in 314ms\r",
    "\u001b[0mFinished running generator.\r",
    "node@factory:/workspace$ cd /workspace/fresh-app/dist\r",
    "node@factory:/workspace/fresh-app/dist$ http-server\r",
    "\u001b[33mStarting up http-server, serving \u001b[36m./\r",
    "\r",
    "\u001b[33mhttp-server version: \u001b[36m14.1.1\r",
    "\r",
    "\u001b[33mhttp-server settings: \r",
    "CORS: \u001b[31mdisabled\r",
    "\u001b[33mCache: \u001b[36m3600 seconds\r",
    "\u001b[33mConnection Timeout: \u001b[36m120 seconds\r",
    "\u001b[33mDirectory Listings: \u001b[36mvisible\r",
    "\u001b[33mAutoIndex: \u001b[36mvisible\r",
    "\u001b[33mServe GZIP Files: \u001b[31mfalse\r",
    "\u001b[33mServe Brotli Files: \u001b[31mfalse\r",
    "\u001b[33mDefault File Extension: \u001b[31mnone\r",
    "\r",
    "\u001b[33mAvailable on:\r",
    "\u001b[0m  http://127.0.0.1:\u001b[32m8080\r",
    "\u001b[0m  http://10.1.0.234:\u001b[32m8080\r",
    "\u001b[0m  http://172.17.0.1:\u001b[32m8080\r",
    "\u001b[0mHit CTRL-C to stop the server\r",
    "\r",
    "[2024-05-06T01:07:33.214Z]  \"\u001b[36mGET\u001b[0m \u001b[36m/\u001b[0m\" \"Mozilla/5.0 (X11; Linux x86_64) AppleWebKit/537.36 (KHTML, like Gecko) HeadlessChrome/121.0.6167.57 Safari/537.36\"\r",
    "(node:104) [DEP0066] DeprecationWarning: OutgoingMessage.prototype._headers is deprecated\r",
    "(Use `node --trace-deprecation ...` to show where the warning was created)\r",
    "[2024-05-06T01:07:33.228Z]  \"\u001b[36mGET\u001b[0m \u001b[36m/assets/index-CWwFz4T6.js\u001b[0m\" \"Mozilla/5.0 (X11; Linux x86_64) AppleWebKit/537.36 (KHTML, like Gecko) HeadlessChrome/121.0.6167.57 Safari/537.36\"\r",
    "[2024-05-06T01:07:33.229Z]  \"\u001b[36mGET\u001b[0m \u001b[36m/assets/index-DDqFzPXY.css\u001b[0m\" \"Mozilla/5.0 (X11; Linux x86_64) AppleWebKit/537.36 (KHTML, like Gecko) HeadlessChrome/121.0.6167.57 Safari/537.36\"\r",
    "[2024-05-06T01:07:33.238Z]  \"\u001b[36mGET\u001b[0m \u001b[36m/vite.svg\u001b[0m\" \"Mozilla/5.0 (X11; Linux x86_64) AppleWebKit/537.36 (KHTML, like Gecko) HeadlessChrome/121.0.6167.57 Safari/537.36\"\r",
    "[2024-05-06T01:07:33.948Z]  \"\u001b[36mGET\u001b[0m \u001b[36m/\u001b[0m\" \"Mozilla/5.0 (X11; Linux x86_64) AppleWebKit/537.36 (KHTML, like Gecko) HeadlessChrome/121.0.6167.57 Safari/537.36\"\r",
    "[2024-05-06T01:07:33.957Z]  \"\u001b[36mGET\u001b[0m \u001b[36m/assets/index-CWwFz4T6.js\u001b[0m\" \"Mozilla/5.0 (X11; Linux x86_64) AppleWebKit/537.36 (KHTML, like Gecko) HeadlessChrome/121.0.6167.57 Safari/537.36\"\r",
    "[2024-05-06T01:07:33.957Z]  \"\u001b[36mGET\u001b[0m \u001b[36m/assets/index-DDqFzPXY.css\u001b[0m\" \"Mozilla/5.0 (X11; Linux x86_64) AppleWebKit/537.36 (KHTML, like Gecko) HeadlessChrome/121.0.6167.57 Safari/537.36\"\r",
    "[2024-05-06T01:07:33.967Z]  \"\u001b[36mGET\u001b[0m \u001b[36m/vite.svg\u001b[0m\" \"Mozilla/5.0 (X11; Linux x86_64) AppleWebKit/537.36 (KHTML, like Gecko) HeadlessChrome/121.0.6167.57 Safari/537.36\"\u001b[1B\u001b[39D"
  ],
  "description": "Fresh Svelte app, automatically generated everyday with \"pnpm create vite --template=svelte-ts\"",
  "buildUrl": "https://github.com/fresh-app/factory/actions/runs/8962540854",
  "frameworkUrl": "https://vitejs.dev/",
  "frameworkDocumentationUrl": "https://vitejs.dev/guide/"
}